moildev/Moildev.py
moildev/__init__.py
moildev/dll/MoilCV.cp310-win_amd64.pyd
moildev/dll/MoilCV.cp36-win_amd64.pyd
moildev/dll/MoilCV.cp37-win_amd64.pyd
moildev/dll/MoilCV.cp38-win_amd64.pyd
moildev/dll/MoilCV.cp39-win_amd64.pyd
moildev/dll/MoilCV.cpython-310-x86_64-linux-gnu.so
moildev/dll/MoilCV.cpython-36m-x86_64-linux-gnu.so
moildev/dll/MoilCV.cpython-37m-x86_64-linux-gnu.so
moildev/dll/MoilCV.cpython-38-x86_64-linux-gnu.so
moildev/dll/MoilCV.cpython-39-x86_64-linux-gnu.so
moildev-4.0.0.dist-info/LICENSE
moildev-4.0.0.dist-info/METADATA
moildev-4.0.0.dist-info/WHEEL
moildev-4.0.0.dist-info/top_level.txt
moildev-4.0.0.dist-info/RECORD
