Metadata-Version: 2.1
Name: moildev
Version: 4.0.0
Summary: moildev is a sophisticated fisheye image processing library
Home-page: https://github.com/MoilOrg/moildev
Author: Haryanto
Author-email: haryanto@o365.mcut.edu.tw
License: MIT License 
Requires-Python: >=3.6
License-File: LICENSE
Requires-Dist: opencv-python
Requires-Dist: numpy
Requires-Dist: setuptools
